{
  "description": "Embark on a journey, where the Twelve Shades reveal the hidden colors of the crypto universe, igniting curiosity and unlocking limitless possibilities in the digital realm. \nEach Color is a 24x24 pixel image",
  "discord_link": "",
  "icon": "https://bafkreibvu335opt5pgyqlvughoxigkru5ofjzpjtgqrfoabasngiitfcgq.ipfs.nftstorage.link/",
  "inscription_icon": "9fef345ab40e20a7b393c574ad1c9e31fc602b877ef674fa7518138a19be098bi0",
  "name": "Cursed Chroma - Unveiling the Twelve Shades of the Dark Spectrum",
  "slug": "cursed-chroma",
  "twitter_link": "https://twitter.com/CursedChroma",
  "website_link": ""
}