{
    "supply": "465",
    "description": "The collection contains unique collectible Inscriptions Dice images of outstanding figures of the Crypto Currency Industry & Film Industry. In the collection, each person appears once. Dice-Art created by using Script, The maximum number of INSCRIPTIONS on BITCOIN ever minted will be 465.",
    "name": "Bitcoin Diceglyphs",
    "slug": "bitcoin-diceglyphs",
    "twitter_link": "https://twitter.com/diceglyphs",
    "discord_link": "https://discord.gg/v4pdh2Zq",
    "website_link": "https://diceglyphs.com/",
    "inscription_icon": "8dea1982d1c320cf26b79c65d8a62b29e9531b76c66800d25790d282c5088b84i0"
}
