{"name": "\u6c34\u6d52.sats", "inscription_icon": "6d2f94dcb84149c9b8ba827dd33c319fb0f75d762a42c68719a2f05466503102i0", "supply": "109", "slug": "shuihu-sats", "description": "\u8fd9\u662f\u4e00\u4e2a\u6c34\u6d52\u4e3b\u9898\u7684.sats\u57df\u540d\u5408\u96c6\uff0c\u5305\u542b\u4e861\u4e2a \u6c34\u6d52.sats \u548c \u4ee5\u6c34\u6d52108\u4e2a\u597d\u6c49\u7684\u540d\u5b57\u547d\u540d\u7684108\u4e2a.sats\u57df\u540d\uff0c\u683c\u5f0f\u91c7\u7528 @sats_names \u5b98\u65b9\u5efa\u8bae\u7684JSON\u683c\u5f0f\u3002", "twitter_link": "", "discord_link": "", "website_link": ""}