{
  "description": "A fully on-chain, hand-typed generative art project that explores the abstract concept of antimatter through visual chaos, forever etched on the Bitcoin blockchain as Ordinals. Serving as a literal algorithmic input behind Antimatter, the hash of the genesis block is one of the two inputs of the main function generating all 5 pieces.",
  "discord_link": "https://discord.gg/VsGxzSh5qW",
  "inscription_icon": "fbfbf62e27dadea7826c0d47da65ff168f1d6ed53f3e393e754bd285f642daadi0",
  "name": "Antimatter",
  "slug": "antimatter",
  "twitter_link": "https://twitter.com/null_ish",
  "website_link": "https://antimatter.nullish.org"
}