{"name": "BXNES SOCIETY: SANCTUM KEYS", "inscription_icon": "e22f5683f7c34f93606c3d402c160140347a85a1c43c182cc956a7d55b8fda77i0", "supply": "5", "slug": "sanctumkeys", "description": "Sanctum Keys: Explore the Sanctum Keys Collection, where art, symbolism, and blockchain intertwine. Own a timeless artifact that grants exclusive access to hidden realms. Join us on an extraordinary journey. ", "twitter_link": "https://twitter.com/BXNESNFT", "discord_link": "", "website_link": "https://bxnesbrc.com"}