{
  "description": "Bitcoin Girls Butterfly is a collection all inscribed on Palindrom sat. Sister collection is Block 78 Bitcoin Girls.",
  "discord_link": "",
  "icon": "https://creator-hub-prod.s3.us-east-2.amazonaws.com/ord-bitcoin-girls-butterfly_pfp_1688849232359.png",
  "name": "🦋Bitcoin Girls Butterfly🦋",
  "slug": "bitcoin-girls-butterfly",
  "twitter_link": "https://twitter.com/ogradation",
  "website_link": "",
  "inscription_icon": "990c73242274a424e40bc094dcc2f9fed1355bc97fe53deb0e0ebecaef559b53i0"
}