{
  "description": "A collection of animated Satoshi ordinals that live in the Satoshi Kingdoms. They have been banished from their home and found new lands to explore. New adventures and trials await Baddies and Goodies... perhaps one day they will unite?",
  "discord_link": "https://discord.gg/NQQawNRHEQ",
  "icon": "https://bafkreiallwte3qnh2ljmgguxz24ghyv33mtyhjhl2c2ezr2gpcnawaauzi.ipfs.nftstorage.link/",
  "inscription_icon": "012c9bb5baecafa0b7c561226e878496a6fb9c1304fddbeeb1789ae91e94f0dbi0",
  "name": "Satoshi Kingdoms",
  "slug": "satoshikingdoms",
  "twitter_link": "https://twitter.com/BaddiesvGoodies",
  "website_link": "https://skwad.info/"
}