{
  "description": "Medieval Empires is a cross-chain strategy game, with Heroes at its core. There are a total of 999 medieval heroes available in the game, including 9 legendary Heroes, 90 elite Heroes, and 900 common Heroes. These Heroes serve as the fundamental units for a player's army, each possessing unique stats and abilities. An army requires a Hero to lead it. The holders of Ordinals Heroes receive taxes generated from the lands they control. In addition, they can earn more Ordinals NFTs after leading their troops to victory.",
  "discord_link": "https://discord.gg/jazG89FzRt",
  "icon": "https://creator-hub-prod.s3.us-east-2.amazonaws.com/ord-heroes_of_medieval_empires_pfp_1692438141580.jpeg",
  "inscription_icon": "3ffbfbea191c9496cc6663b3e43fca435b903b8075b8e4d1bd2937b0fe2d2347i0",
  "name": "Heroes of Medieval Empires",
  "slug": "heroes_of_medieval_empires",
  "twitter_link": "https://twitter.com/Heroes_of_ME",
  "website_link": "https://www.medievalempires.com/"
}