{
  "description": "The Singularity Network Server collection consists of 177 Network Servers. There appears to be a glitch with some of the servers...A Singularity Genesis Ordinal is required to be able to use this device.",
  "discord_link": "https://discord.gg/btcai",
  "icon": "https://creator-hub-prod.s3.us-east-2.amazonaws.com/ord-singularity-network_pfp_1690831008744.png",
  "name": "Singularity Network Server",
  "slug": "singularity-network",
  "twitter_link": "https://twitter.com/ordsingularity",
  "website_link": "https://btcai.shop"
}