[
  {
    "id": "35026f6f1d415485715c238ffd5a599af6c1c070d6270721e99725ad10581fbfi0",
    "meta": {
      "name": "The Third Eye #3",
      "high_res_img_url": "http://www.crypartists.com/Ordinals/ThirdEye/ThirdEye3.JPG"
    }
  },
  {
    "id": "9d9aeea2e5ddfe505ce99b18825aef23a643ce7341d7d51aebe3760b582ad65fi0",
    "meta": {
      "name": "The Third Eye #2",
      "high_res_img_url": "http://www.crypartists.com/Ordinals/ThirdEye/ThirdEye2.JPG"
    }
  },
  {
    "id": "edbc271a489823782ac558a9d2952f6449bf3e3351e20d226355e28d776a2cd7i0",
    "meta": {
      "name": "The Third Eye #1",
      "high_res_img_url": "http://www.crypartists.com/Ordinals/ThirdEye/ThirdEye1.png"
    }
  },
  {
    "id": "1a79f8bcd20f46b35d5e3020a1790dd9336fa85cee89dd29033f0ddfd456577bi0",
    "meta": {
      "name": "The Third Eye #4",
      "high_res_img_url": "http://www.crypartists.com/Ordinals/ThirdEye/ThirdEye4.JPG"
    }
  }
]