{
  "description": "The First Doge PFP project inscribed onto the bitcoin blockchain with a genesis collection of 100 Doges under 50k inscriptions! Be sure to check the main collection\nAnd our sister LTC collection under 25k",
  "discord_link": "https://discord.gg/VZy85pasdN",
  "icon": "https://bafkreiawf5vcun2bnrougrvbycjg6d5tg3z4m3gvjecj6kfraaqjl6pohe.ipfs.nftstorage.link/",
  "name": "Ordinal Doge Genesis",
  "slug": "ordinaldogegenesis",
  "twitter_link": "https://twitter.com/ordinal_doge",
  "website_link": "",
  "inscription_icon": "6385f0f7049f2be2f0989c7e991f2e7df373a4405d054400fbcc0ed0f6c82dffi0"
}