{
  "description": "Web3 game \"cryptofantasy\" based on CryptoNinja, pixel art in monaco2dx style.\n*This is not an official collection announcement as the CryptoFantasy development team. monako2dx personal activity.",
  "discord_link": "",
  "icon": "https://bafkreiemf7ewxfxkggtasru3v7ijzit5ftvite27a322vl7twsf7kzonzi.ipfs.nftstorage.link/",
  "name": "CryptoFantasy - pixel fanart collections",
  "slug": "cryptofantasy-pfc",
  "twitter_link": "https://twitter.com/m2dxnft",
  "website_link": "",
  "inscription_icon": "0b32ccd15487f61864f2811da20cb24424874198c6e9d0ef58476f97424fa966i0"
}